Workbook

Sheet 注文履歴
C3: 注文ID | D3: 日付 | E3: 顧客名 | F3: 商品名 | G3: 単価 | H3: 数量 | I3: 金額 | J3: 支払方法
C4: 1001 | D4: 2025/11/02 | E4: 佐藤太郎 | F4: プリンター | G4: 15000 | H4: 7 | I4: =G4*H4 -> 105000 | J4: 現金
C5: 1002 | D5: 2025/11/03 | E5: 鈴木花子 | F5: マウス | G5: 2000 | H5: 3 | I5: =G5*H5 -> 6000 | J5: 電子マネー
C6: 1003 | D6: 2025/11/01 | E6: 佐藤太郎 | F6: マウス | G6: 2000 | H6: 8 | I6: =G6*H6 -> 16000 | J6: 現金
C7: 1004 | D7: 2025/11/09 | E7: 加藤恵 | F7: ノートPC | G7: 120000 | H7: 8 | I7: =G7*H7 -> 960000 | J7: 現金
C8: 1005 | D8: 2025/11/09 | E8: 伊藤陽子 | F8: キーボード | G8: 5000 | H8: 4 | I8: =G8*H8 -> 20000 | J8: 銀行振込
C9: 1006 | D9: 2025/11/01 | E9: 田中一郎 | F9: スマートフォン | G9: 80000 | H9: 8 | I9: =G9*H9 -> 640000 | J9: 銀行振込
C10: 1007 | D10: 2025/11/03 | E10: 山田次郎 | F10: タブレット | G10: 40000 | H10: 7 | I10: =G10*H10 -> 280000 | J10: クレジット
C11: 1008 | D11: 2025/11/07 | E11: 鈴木花子 | F11: タブレット | G11: 40000 | H11: 4 | I11: =G11*H11 -> 160000 | J11: 銀行振込
C12: 1009 | D12: 2025/11/01 | E12: 渡辺真 | F12: マウス | G12: 2000 | H12: 2 | I12: =G12*H12 -> 4000 | J12: クレジット
C13: 1010 | D13: 2025/11/09 | E13: 高橋美咲 | F13: タブレット | G13: 40000 | H13: 3 | I13: =G13*H13 -> 120000 | J13: 現金
C14: 1011 | D14: 2025/11/02 | E14: 佐藤太郎 | F14: キーボード | G14: 5000 | H14: 7 | I14: =G14*H14 -> 35000 | J14: クレジット
C15: 1012 | D15: 2025/11/04 | E15: 鈴木花子 | F15: スマートフォン | G15: 80000 | H15: 2 | I15: =G15*H15 -> 160000 | J15: 電子マネー
... C33: 1030 | D33: 2025/11/08 | E33: 佐藤太郎 | F33: マウス | G33: 2000 | H33: 7 | I33: =G33*H33 -> 14000 | J33: 銀行振込

Sheet 基本集計
B3: 基本集計
B4: 項目 | C4: 集計結果
B5: 総売上 | C5: =SUM(注文履歴!I4:I33) -> 6166000
B6: 平均単価 | C6: =AVERAGE(注文履歴!G4:G33) -> 39400
B7: 平均購入金額 | C7: =AVERAGE(注文履歴!I4:I33) -> 205533.33
B8: 最大数量 | C8: =MAX(注文履歴!H4:H33) -> 8
B9: 最小金額 | C9: =MIN(注文履歴!I4:I33) -> 4000

Sheet 条件付き合計（例）
B2: 社員ID | C2: 氏名 | D2: 部署 | E2: 勤務日数 | F2: 残業時間 | H2: 練習内容 | I2: 条件 | J2: 使用関数例 | K2: 結果
B3: E001 | C3: 佐藤太郎 | D3: 営業 | E3: 18 | F3: 11 | H3: 営業部の勤務日数合計 | I3: 営業 | J3: =SUMIF(D3:D12,"営業",E3:E12) | K3: =SUMIF(D3:D12,"営業",E3:E12) -> 80
B4: E002 | C4: 鈴木花子 | D4: 経理 | E4: 19 | F4: 3 | H4: 開発部の残業時間合計 | I4: 開発 | J4: =SUMIF(D3:D12,"開発",？) | K4: =SUMIF(D3:D12,"開発",F3:F12) -> 15
B5: E003 | C5: 田中一郎 | D5: 開発 | E5: 23 | F5: 1 | H5: 勤務日数20日以上の残業時間合計 | I5: 20日以上 | J5: =SUMIF(E3:E12,？,？) | K5: =SUMIF(E3:E12,">=20",F3:F12) -> 16
B6: E004 | C6: 山田次郎 | D6: 営業 | E6: 22 | F6: 6
B7: E005 | C7: 高橋美咲 | D7: 営業 | E7: 18 | F7: 1
B8: E006 | C8: 中村健 | D8: 開発 | E8: 19 | F8: 8
B9: E007 | C9: 伊藤陽子 | D9: 営業 | E9: 22 | F9: 3
B10: E008 | C10: 渡辺真 | D10: 総務 | E10: 19 | F10: 7
B11: E009 | C11: 小林翔 | D11: 経理 | E11: 18 | F11: 12
B12: E010 | C12: 加藤恵 | D12: 開発 | E12: 23 | F12: 6

Sheet 条件付き合計
B2: 条件付き合計
C3: 条件
B4: 商品名が「スマートフォン」 の数量合計 | C4: スマートフォン | D4: =SUMIF(注文履歴!F4:F33,"スマートフォン",注文履歴!H4:H33) -> 31
B5: 日付が2025/11/03の金額合計 | C5: 2025/11/03 | D5: =SUMIF(注文履歴!D4:D33,C5,注文履歴!I4:I33) -> 1921000 | E5: ※C5を参照するか，DATE関数を使う
B6: 金額が20,000以上の数量合計 | C6: >=20000 | D6: =SUMIF(注文履歴!I4:I33,">=20000",注文履歴!H4:H33) -> 124
B7: 支払い方法が電子マネーの金額合計 | C7: 電子マネー | D7: =SUMIF(注文履歴!J4:J33,"電子マネー",注文履歴!I4:I33) -> 1096000

Sheet 丸め
B2: 値 | C2: 桁数 | D2: ROUND関数 | E2: ROUNDDOWN関数 | F2: ROUNDUP関数
B3: 140.178 | C3: 0 | D3: =ROUND(B3,C3) -> 140 | E3: =ROUNDDOWN(B3,C3) -> 140 | F3: =ROUNDUP(B3,C3) -> 141
B4: 140.178 | C4: 1 | D4: =ROUND(B4,C4) -> 140.2 | E4: =ROUNDDOWN(B4,C4) -> 140.1 | F4: =ROUNDUP(B4,C4) -> 140.2
B5: 140.178 | C5: 2 | D5: =ROUND(B5,C5) -> 140.18 | E5: =ROUNDDOWN(B5,C5) -> 140.17 | F5: =ROUNDUP(B5,C5) -> 140.18
B6: 140.178 | C6: -1 | D6: =ROUND(B6,C6) -> 140 | E6: =ROUNDDOWN(B6,C6) -> 140 | F6: =ROUNDUP(B6,C6) -> 150
B7: 140.178 | C7: -2 | D7: =ROUND(B7,C7) -> 100 | E7: =ROUNDDOWN(B7,C7) -> 100 | F7: =ROUNDUP(B7,C7) -> 200

Sheet 文字列操作
B2: 学籍番号 | C2: 入学年度 | D2: 学部 | E2: 学科番号 | F2: 個人番号
B3: 23B3456 | C3: =LEFT(B3,2) -> 23 | D3: =MID(B3,3,1) -> B | E3: =MID(B3,4,1) -> 3 | F3: =RIGHT(B3,3) -> 456
B4: 25A7123 | C4: =LEFT(B4,2) -> 25 | D4: =MID(B4,3,1) -> A | E4: =MID(B4,4,1) -> 7 | F4: =RIGHT(B4,3) -> 123
B5: ↑自分の学籍番号を入力してください
